{
  "App": {
        "cei": {
              "url": "https://ceiapp.b3.com.br/CEI_Responsivo/login.aspx",
              "earningUrl":"https://ceiapp.b3.com.br/CEI_Responsivo/ConsultarProventos.aspx",
              "headless": false,
              "delay": 300,
              "tags":{
                "login": "'ctl00$ContentPlaceHolder1$txtLogin'",
                "password": "'ctl00$ContentPlaceHolder1$txtSenha'",
                "btnLogin": "'ctl00$ContentPlaceHolder1$btnLogar'",
                "institution":"'ctl00$ContentPlaceHolder1$ddlAgentes'"
              }
        }
  }
}
